events_framework/__init__.py
events_framework/apps.py
events_framework/decorators.py
events_framework/manager.py
events_framework/models.py
events_framework/utils.py
events_framework/management/__init__.py
events_framework/management/commands/__init__.py
events_framework/management/commands/process_events.py
django_events_framework-0.0.13.dist-info/AUTHORS
django_events_framework-0.0.13.dist-info/LICENSE
django_events_framework-0.0.13.dist-info/METADATA
django_events_framework-0.0.13.dist-info/WHEEL
django_events_framework-0.0.13.dist-info/top_level.txt
django_events_framework-0.0.13.dist-info/RECORD
